examples/experements/__init__.py
examples/experements/conftest.py
examples/experements/test_1.py
examples/experements/test_kek.py
examples/experements/transformer.py
examples/replace_asserts/__init__.py
examples/replace_asserts/conftest.py
examples/replace_asserts/test_simple_assert.py
examples/replace_asserts/transformer.py
pytest_ast_transformer/__init__.py
pytest_ast_transformer/ast_manager.py
pytest_ast_transformer/exceptions.py
pytest_ast_transformer/newhooks.py
pytest_ast_transformer/plugin.py
pytest_ast_transformer/transformer/__init__.py
pytest_ast_transformer/transformer/base.py
pytest_ast_transformer/transformer/code.py
pytest_ast_transformer/transformer/pytest_transformer.py
pytest_ast_transformer/transformer/utils.py
pytest_ast_transformer/transformer/wrapper.py
pytest_ast_transformer-1.0.3.dist-info/METADATA
pytest_ast_transformer-1.0.3.dist-info/WHEEL
pytest_ast_transformer-1.0.3.dist-info/entry_points.txt
pytest_ast_transformer-1.0.3.dist-info/top_level.txt
pytest_ast_transformer-1.0.3.dist-info/RECORD
