Metadata-Version: 1.1
Name: pytest-ast-transformer
Version: 1.0.3
Summary: UNKNOWN
Home-page: https://github.com/okorolev/pytest-ast-transformer
Author: okorolev
Author-email: johnnyprobel@gmail.com
License: UNKNOWN
Keywords: pytest,ast,transformer,refactoring,testing,debug
Platform: UNKNOWN
Classifier: Framework :: Pytest
Classifier: Programming Language :: Python :: 3
Classifier: Development Status :: 3 - Alpha
